g2p_greek/__init__.py
g2p_greek/__main__.py
g2p_greek/dictionary.py
g2p_greek/digits_to_words.py
g2p_greek/english_rules.py
g2p_greek/g2p_greek.py
g2p_greek/phoneme_conversion.py
g2p_greek/prefixes.py
g2p_greek/py.typed
g2p_greek/rules.py
g2p_greek/sort.py
g2p_greek/utils.py
g2p_greek-0.0.2a0.dist-info/entry_points.txt
g2p_greek-0.0.2a0.dist-info/LICENSE
g2p_greek-0.0.2a0.dist-info/WHEEL
g2p_greek-0.0.2a0.dist-info/METADATA
g2p_greek-0.0.2a0.dist-info/RECORD
