Metadata-Version: 2.1
Name: g2p-greek
Version: 0.0.2a0
Summary: Grapheme to Phoneme conversion for Greek.
Home-page: https://github.com/geoph9/GraphemeToPhoneme-Greek
License: MIT
Author: K. Georgios
Author-email: geoph9@protonmail.com
Requires-Python: >=3.7,<4.0
Classifier: Development Status :: 2 - Pre-Alpha
Classifier: License :: OSI Approved :: MIT License
Classifier: Programming Language :: Python :: 3
Classifier: Programming Language :: Python :: 3.10
Classifier: Programming Language :: Python :: 3.7
Classifier: Programming Language :: Python :: 3.8
Classifier: Programming Language :: Python :: 3.9
Project-URL: Changelog, https://github.com/geoph9/g2p_greek/releases
Project-URL: Repository, https://github.com/geoph9/GraphemeToPhoneme-Greek
